isaExplorer/__init__.py
isaExplorer/isaExplorer.py
isaExplorer/tests/__init__.py
isaExplorer/tests/test_exploreISA.py
isaExplorer-0.1.0.dist-info/METADATA
isaExplorer-0.1.0.dist-info/RECORD
isaExplorer-0.1.0.dist-info/WHEEL
isaExplorer-0.1.0.dist-info/top_level.txt
isaExplorer-0.1.0.dist-info/zip-safe
