Metadata-Version: 2.1
Name: isaExplorer
Version: 0.1.0
Summary: Explore and manipulate the contents of ISATAB files
Home-page: http://github.com/phenomecentre/isaexplorer
Author: Noureddin Sadawi
Author-email: n.sadawi@gmail.com
License: MIT
Platform: UNKNOWN
Classifier: Programming Language :: Python
Classifier: Programming Language :: Python :: 3.6
Classifier: Intended Audience :: Science/Research
Classifier: License :: OSI Approved :: MIT License
Classifier: Operating System :: OS Independent
Classifier: Topic :: Scientific/Engineering :: Bio-Informatics
Requires-Dist: isatools (>=0.9.0)
